any2csv/__init__.py
any2csv/main.py
any2csv-0.3.6.dist-info/DESCRIPTION.rst
any2csv-0.3.6.dist-info/METADATA
any2csv-0.3.6.dist-info/RECORD
any2csv-0.3.6.dist-info/WHEEL
any2csv-0.3.6.dist-info/entry_points.txt
any2csv-0.3.6.dist-info/metadata.json
any2csv-0.3.6.dist-info/top_level.txt
