Metadata-Version: 2.0
Name: any2csv
Version: 0.3.6
Summary: A tool to generate csv file from a list of python instances
Home-page: https://bitbucket.org/faide/any2csv
Author: Jerome Collette, Florent Aide
Author-email: collette.jerome@gmail.com, florent.aide@gmail.com
License: BSD License
Keywords: csv python
Platform: UNKNOWN
Classifier: Development Status :: 5 - Production/Stable
Classifier: Intended Audience :: Developers
Classifier: License :: OSI Approved :: BSD License
Classifier: Operating System :: OS Independent
Classifier: Programming Language :: Python
Classifier: Topic :: Software Development :: Libraries :: Python Modules
Classifier: Topic :: Text Processing :: General
Requires-Dist: pyjon.utils
Requires-Dist: six
Requires-Dist: any2 (>=0.3.1)
